antimeridian/__init__.py
antimeridian/_cli.py
antimeridian/_implementation.py
antimeridian/py.typed
antimeridian-0.4.3.dist-info/METADATA
antimeridian-0.4.3.dist-info/WHEEL
antimeridian-0.4.3.dist-info/entry_points.txt
antimeridian-0.4.3.dist-info/licenses/LICENSE
antimeridian-0.4.3.dist-info/RECORD
