Metadata-Version: 2.4
Name: antimeridian
Version: 0.4.3
Summary: Correct GeoJSON geometries that cross the 180th meridian
Project-URL: Documentation, https://www.gadom.ski/antimeridian
Project-URL: Github, https://github.com/gadomski/antimeridian
Project-URL: Issues, https://github.com/gadomski/antimeridian/issues
Project-URL: Changelog, https://github.com/gadomski/antimeridian/blob/main/CHANGELOG.md
Author-email: Pete Gadomski <pete.gadomski@gmail.com>
License: Apache-2.0
License-File: LICENSE
Keywords: antimeridian,geojson,shapely
Classifier: Development Status :: 4 - Beta
Classifier: Programming Language :: Python :: 3
Classifier: Programming Language :: Python :: 3.10
Classifier: Programming Language :: Python :: 3.11
Classifier: Programming Language :: Python :: 3.12
Classifier: Programming Language :: Python :: 3.13
Requires-Python: >=3.10
Requires-Dist: numpy>=1.22.4
Requires-Dist: shapely>=2.0
Provides-Extra: cli
Requires-Dist: click>=8.1.6; extra == 'cli'
